flask_wangEditor/__init__.py
flask_wangEditor/fields.py
flask_wangEditor/utils.py
Flask_wangEditor-0.0.4.0.dist-info/LICENSE
Flask_wangEditor-0.0.4.0.dist-info/METADATA
Flask_wangEditor-0.0.4.0.dist-info/WHEEL
Flask_wangEditor-0.0.4.0.dist-info/top_level.txt
Flask_wangEditor-0.0.4.0.dist-info/RECORD
