Metadata-Version: 2.1
Name: Flask-wangEditor
Version: 0.0.4.0
Summary: wangEditor integration for Flask.
Home-page: https://github.com/Nuctori/flask_wangEditor
Author: Nuctori
Author-email: Nuctori@foxmail.com
License: MIT
Platform: any
Classifier: Environment :: Web Environment
Classifier: Intended Audience :: Developers
Classifier: License :: OSI Approved :: MIT License
Classifier: Operating System :: OS Independent
Classifier: Programming Language :: Python
Classifier: Programming Language :: Python :: 3
Classifier: Programming Language :: Python :: 3.6
Classifier: Topic :: Internet :: WWW/HTTP :: Dynamic Content
Classifier: Topic :: Software Development :: Libraries :: Python Modules
License-File: LICENSE
Requires-Dist: Flask
